Workbook

Sheet 📊 Dashboard
A1: 🇮🇪 2026 Irish Student & Part-Time Worker Budget Tracker
A2: Updated automatically from the Monthly Tracker tab — no manual entry needed here.
A4: ='📅 Monthly Tracker'!C10 -> 0 | D4: ='📅 Monthly Tracker'!C39 -> 0 | G4: ='📅 Monthly Tracker'!H45 -> Break even 😅
A5: 💰 Total Monthly Income | D5: 📤 Total Monthly Expenses | G5: 🍺 Pints Saved
A6: ='📅 Monthly Tracker'!C41 -> 0
A7: ✅ Remaining Balance This Month
A9: ='📅 Monthly Tracker'!H49 -> 0 days to payday ⏳
A10: ⏳ Days Until Next SUSI / Payday
A12: 🚦 Category Spend vs. Budget (Traffic Light)
A13: Category | B13: Budgeted | C13: Actual | D13: Remaining | E13: % Used | F13: Status
A14: 🏠 Rent | B14: ='📅 Monthly Tracker'!D14 -> 600 | C14: ='📅 Monthly Tracker'!C14 -> 0 | D14: =B14-C14 -> 600 | E14: =IF(B14=0,"N/A",C14/B14) -> 0 | F14: =IF(B14=0,"⚪ N/A",IF(C14/B14<=0.8,"🟢 On Track",IF(C14/B14<=1,"🟡 Watch Out","🔴 Over Budget!"))) -> 🟢 On Track
A15: 🎓 Student Contrib. | B15: ='📅 Monthly Tracker'!D15 -> 0 | C15: ='📅 Monthly Tracker'!C15 -> 0 | D15: =B15-C15 -> 0 | E15: =IF(B15=0,"N/A",C15/B15) -> N/A | F15: =IF(B15=0,"⚪ N/A",IF(C15/B15<=0.8,"🟢 On Track",IF(C15/B15<=1,"🟡 Watch Out","🔴 Over Budget!"))) -> ⚪ N/A
A16: ⚡ Utilities/Bins | B16: ='📅 Monthly Tracker'!D16 -> 60 | C16: ='📅 Monthly Tracker'!C16 -> 0 | D16: =B16-C16 -> 60 | E16: =IF(B16=0,"N/A",C16/B16) -> 0 | F16: =IF(B16=0,"⚪ N/A",IF(C16/B16<=0.8,"🟢 On Track",IF(C16/B16<=1,"🟡 Watch Out","🔴 Over Budget!"))) -> 🟢 On Track
A17: 🚌 Transport | B17: ='📅 Monthly Tracker'!D24 -> 120 | C17: ='📅 Monthly Tracker'!C24 -> 0 | D17: =B17-C17 -> 120 | E17: =IF(B17=0,"N/A",C17/B17) -> 0 | F17: =IF(B17=0,"⚪ N/A",IF(C17/B17<=0.8,"🟢 On Track",IF(C17/B17<=1,"🟡 Watch Out","🔴 Over Budget!"))) -> 🟢 On Track
A18: 🛒 Groceries | B18: ='📅 Monthly Tracker'!D28 -> 180 | C18: ='📅 Monthly Tracker'!C28 -> 0 | D18: =B18-C18 -> 180 | E18: =IF(B18=0,"N/A",C18/B18) -> 0 | F18: =IF(B18=0,"⚪ N/A",IF(C18/B18<=0.8,"🟢 On Track",IF(C18/B18<=1,"🟡 Watch Out","🔴 Over Budget!"))) -> 🟢 On Track
A19: 🍻 Social | B19: ='📅 Monthly Tracker'!D29 -> 80 | C19: ='📅 Monthly Tracker'!C29 -> 0 | D19: =B19-C19 -> 80 | E19: =IF(B19=0,"N/A",C19/B19) -> 0 | F19: =IF(B19=0,"⚪ N/A",IF(C19/B19<=0.8,"🟢 On Track",IF(C19/B19<=1,"🟡 Watch Out","🔴 Over Budget!"))) -> 🟢 On Track
A20: ☔ Rainy Day Fund | B20: ='📅 Monthly Tracker'!D36 -> 50 | C20: ='📅 Monthly Tracker'!C36 -> 0 | D20: =B20-C20 -> 50 | E20: =IF(B20=0,"N/A",C20/B20) -> 0 | F20: =IF(B20=0,"⚪ N/A",IF(C20/B20<=0.8,"🟢 On Track",IF(C20/B20<=1,"🟡 Watch Out","🔴 Over Budget!"))) -> 🟢 On Track

Sheet 📅 Monthly Tracker
A1: 📅 Monthly Budget Tracker — Enter your data in BLUE cells
A2: Month / Year: | B2: =DATE(2026,1,1) -> 46023
A4: 💰 INCOME
A5: Income Source | C5: Amount Received (€) | D5: Expected (€) | E5: Notes
A6: 🎓 SUSI Grant (Monthly Equiv.) | D6: 495 | E6: SUSI pays ~€4,455/yr over 9 months (Sept–May). Enter 0 in June–Aug.
A7: 💼 Part-Time Wages | D7: 600 | E7: ~€15/hr × hrs worked. Enter net (after tax/USC/PRSI).
A8: 🎁 One-Off (Birthday/Tax Refund) | D8: 0 | E8: Lump sums only — don't rely on these for recurring bills!
A10: ✅ TOTAL INCOME | C10: =SUM(C6:C8) -> 0 | D10: =SUM(D6:D8) -> 1095
A12: 🏠 HOUSING EXPENSES
A13: Expense | C13: Actual (€) | D13: Budget (€) | E13: Notes
A14: 🏠 Rent | D14: 600 | E14: HAP-eligible? Check hap.ie
A15: 🎓 Student Contribution Fee | D15: 0 | E15: €3,000/yr — enter monthly spread if paying in instalments
A16: ⚡ Utilities / Bins | D16: 60 | E16: Electric Ireland / Bord Gáis — split with housemates!
A17: Housing Sub-Total | C17: =SUM(C14:C16) -> 0 | D17: =SUM(D14:D16) -> 660
A19: 🚌 TRANSPORT EXPENSES
A20: Expense | C20: Actual (€) | D20: Budget (€) | E20: Notes
A21: 💳 Leap Card Top-Ups | D21: 60 | E21: Student Leap = 50% off. Top up at Payzone shops.
A22: 🚆 Iarnród Éireann / Bus Éireann | D22: 40 | E22: Young Adult Card = 50% off intercity. Book ahead!
A23: 🚗 Fuel / Taxi | D23: 20 | E23: Splitting an Uber? Enter your share only.
A24: Transport Sub-Total | C24: =SUM(C21:C23) -> 0 | D24: =SUM(D21:D23) -> 120
A26: 🛒 LIFESTYLE EXPENSES
A27: Expense | C27: Actual (€) | D27: Budget (€) | E27: Notes
A28: 🛒 Groceries (Aldi/Lidl/Tesco) | D28: 180 | E28: ~€45/week is very achievable in Aldi. Meal prep = savings.
A29: 🍻 Social (Pints/Nights Out) | D29: 80 | E29: A pint in Dublin = ~€6.50. That's your benchmark.
A30: 🏫 Societies / College Expenses | D30: 20 | E30: Socs fees, printing, stationery etc.
A31: 📱 Phone / Subscriptions | D31: 30 | E31: 48, Three, Vodafone PAYG — shop around!
A32: Lifestyle Sub-Total | C32: =SUM(C28:C31) -> 0 | D32: =SUM(D28:D31) -> 310
A34: ☔ SAVINGS & RAINY DAY FUND
A35: Category | C35: Actual (€) | D35: Target (€) | E35: Notes
A36: ☔ Rainy Day Fund Contribution | D36: 50 | E36: Aim for €500–€1,000 emergency buffer. Even €10/week helps.
A37: 🎯 Savings Goal (Holiday etc.) | D37: 30 | E37: Label your goal here — it makes it real!
A39: 📤 TOTAL EXPENSES (Actual) | C39: =C17+C24+C32+C36+C37 -> 0 | D39: =D17+D24+D32+D36+D37 -> 1170
A40: 🏦 BUDGET VARIANCE (Budget – Actual) | C40: =D39-C39 -> 1170
A41: 💰 NET REMAINING BALANCE | C41: =C10-C39 -> 0
A44: 🍺 THE FUN FORMULAS
A45: 🍺 Pints You Could Buy With Your Savings This Month | H45: =IF(C41>0,FLOOR(C41/6.5,1)&" pints 🍺",IF(C41=0,"Break even 😅","You're in the red, pal 😬")) -> Break even 😅
A46: 📅 SUSI Payment Date (enter the next one): | E46: =DATE(2026,2,1) -> 46054
A47: 💼 Next Payday (enter your payday): | E47: =DATE(2026,1,25) -> 46047
A48: ⏳ Days Until Next Payment (whichever comes first): | H48: =MAX(0,MIN(E46,E47)-TODAY())&" days" -> 0 days
H49: =MAX(0,MIN(E46,E47)-TODAY())&" days to payday ⏳" -> 0 days to payday ⏳

Sheet 🎓 SUSI Schedule
A1: 🎓 SUSI Grant Payment Schedule 2025–2026
A2: Annual Grant Amount (€) — enter your award letter figure:
A3: Annual Award (€): | B3: 4455 | C3: Monthly Payment: | D3: =B3/9 -> 495
A5: Month | B5: Expected Date | C5: Amount (€) | D5: Received (€) | E5: Status
A6: September 2025 | B6: 01/09/2025 | C6: =$D$3 -> 495 | D6: 0 | E6: =IF(D6=0,"⏳ Pending",IF(D6>=C6,"✅ Received","⚠️ Short — check with SUSI")) -> ⏳ Pending
A7: October 2025 | B7: 01/10/2025 | C7: =$D$3 -> 495 | D7: 0 | E7: =IF(D7=0,"⏳ Pending",IF(D7>=C7,"✅ Received","⚠️ Short — check with SUSI")) -> ⏳ Pending
A8: November 2025 | B8: 01/11/2025 | C8: =$D$3 -> 495 | D8: 0 | E8: =IF(D8=0,"⏳ Pending",IF(D8>=C8,"✅ Received","⚠️ Short — check with SUSI")) -> ⏳ Pending
A9: December 2025 | B9: 01/12/2025 | C9: =$D$3 -> 495 | D9: 0 | E9: =IF(D9=0,"⏳ Pending",IF(D9>=C9,"✅ Received","⚠️ Short — check with SUSI")) -> ⏳ Pending
A10: January 2026 | B10: 01/01/2026 | C10: =$D$3 -> 495 | D10: 0 | E10: =IF(D10=0,"⏳ Pending",IF(D10>=C10,"✅ Received","⚠️ Short — check with SUSI")) -> ⏳ Pending
A11: February 2026 | B11: 01/02/2026 | C11: =$D$3 -> 495 | D11: 0 | E11: =IF(D11=0,"⏳ Pending",IF(D11>=C11,"✅ Received","⚠️ Short — check with SUSI")) -> ⏳ Pending
A12: March 2026 | B12: 01/03/2026 | C12: =$D$3 -> 495 | D12: 0 | E12: =IF(D12=0,"⏳ Pending",IF(D12>=C12,"✅ Received","⚠️ Short — check with SUSI")) -> ⏳ Pending
A13: April 2026 | B13: 01/04/2026 | C13: =$D$3 -> 495 | D13: 0 | E13: =IF(D13=0,"⏳ Pending",IF(D13>=C13,"✅ Received","⚠️ Short — check with SUSI")) -> ⏳ Pending
A14: May 2026 | B14: 01/05/2026 | C14: =$D$3 -> 495 | D14: 0 | E14: =IF(D14=0,"⏳ Pending",IF(D14>=C14,"✅ Received","⚠️ Short — check with SUSI")) -> ⏳ Pending
A15: TOTAL SUSI (Full Year) | C15: =SUM(C6:C14) -> 4455 | D15: =SUM(D6:D14) -> 0

Sheet 🔧 Formula Reference
A1: 🔧 Formula Reference — Copy-Paste Ready
A2: Formula Name | B2: Formula | C2: What It Does
A3: Remaining Balance | B3: '=C9-C34 | C3: Total Income minus Total Expenses on Monthly Tracker
A4: Days Until Next Payday | B4: '=MAX(0,MIN(E41,E42)-TODAY())&" days" | C4: Counts down to the sooner of SUSI or Payday
A5: Pint-Equivalent Savings | B5: '=IF(C36>0,FLOOR(C36/6.5,1)&" pints 🍺","Break even or over budget") | C5: Converts your surplus into Dublin pint-units (€6.50 each)
A6: SUSI Monthly Amount | B6: '=AnnualAward/9 | C6: Divides annual SUSI award over 9 payment months
A7: Traffic Light — On Track | B7: '=IF(Actual/Budget<=0.8,"🟢 On Track",IF(Actual/Budget<=1,"🟡 Watch Out","🔴 Over Budget!")) | C7: Green ≤80% used, Amber ≤100%, Red >100%
A8: Budget Variance | B8: '=Budgeted - Actual | C8: Positive = under budget (good). Negative = over budget.
A9: SUSI Status Check | B9: '=IF(D6=0,"⏳ Pending",IF(D6>=C6,"✅ Received","⚠️ Short")) | C9: Checks if SUSI payment arrived and was the right amount
A10: Part-Time Wage Estimate | B10: '=HourlyRate * HoursWorked | C10: Enter €15 as rate and your contracted hours

Sheet 📖 README — Quick Start
A1: 📖 Quick Start Guide — 3 Steps to Financial Freedom (or at least fewer overdrafts)
A4: STEP 1 — 🎯 Set Your Budgets
A5: ▶ | B5: Go to the '📅 Monthly Tracker' tab.
A6: ▶ | B6: In the BLUE cells under the 'Budget (€)' column (Column D), enter how much you PLAN to spend in each category.
A7: ▶ | B7: If you get SUSI, open '🎓 SUSI Schedule' and enter your annual award amount in cell B3. It will auto-calculate your monthly payments.
A8: ▶ | B8: Tip: Be honest here. A budget built on fantasy is just a wish list.
A11: STEP 2 — 💶 Log Your Spending (Weekly is Grand)
A12: ▶ | B12: Once a week, sit down for 5 minutes and update the BLUE 'Actual (€)' cells (Column C) on the Monthly Tracker.
A13: ▶ | B13: Your Remaining Balance and the Dashboard traffic lights will update instantly.
A14: ▶ | B14: Enter your next SUSI date in cell E41 and your Payday in E42 — the countdown timer will do the rest.
A15: ▶ | B15: Tip: Link your bank app notifications to remind you — every time you spend, note it down before you forget.
A18: STEP 3 — 📊 Review the Dashboard Monthly
A19: ▶ | B19: On the last day of each month, open the '📊 Dashboard' tab.
A20: ▶ | B20: Check the Traffic Lights: 🟢 = sound, 🟡 = rein it in, 🔴 = we need to talk.
A21: ▶ | B21: Check your 🍺 Pint-Equivalent score — a fun way to track real savings!
A22: ▶ | B22: Copy the Monthly Tracker tab (right-click → 'Copy to') to start a fresh month. Keep old months for comparison.
A23: ▶ | B23: Tip: Set a monthly calendar reminder — 'Budget Review' — so it becomes a habit, not a chore.
A26: 💡 Need help? Open the '🔧 Formula Reference' tab to see exactly what every formula does and where to paste it.
